rocktrie/__init__.py
rocktrie-0.0.1.dist-info/LICENSE
rocktrie-0.0.1.dist-info/METADATA
rocktrie-0.0.1.dist-info/WHEEL
rocktrie-0.0.1.dist-info/top_level.txt
rocktrie-0.0.1.dist-info/RECORD
