Metadata-Version: 2.1
Name: rocktrie
Version: 0.0.1
Summary: Trie on RocksDB
Author-email: Vee Satayamas <vsatayamas@gmail.com>
Project-URL: homepage, https://git.sr.ht/~veer66/rocktrie
Keywords: trie
Classifier: Programming Language :: Python :: 3
Classifier: License :: OSI Approved :: Apache Software License
Classifier: Intended Audience :: Developers
Classifier: Operating System :: OS Independent
Classifier: Topic :: Software Development :: Libraries
License-File: LICENSE
Requires-Dist: rocksdb (==0.7)
Requires-Dist: orjson (==3.8.1)
